zipload.py
zipload-0.1.0.dist-info/LICENSE
zipload-0.1.0.dist-info/WHEEL
zipload-0.1.0.dist-info/METADATA
zipload-0.1.0.dist-info/RECORD
